{
  "id": "4f33c49e-872c-4fc1-8b06-d4dbc3225495",
  "prevId": "00000000-0000-0000-0000-000000000000",
  "version": "7",
  "dialect": "postgresql",
  "tables": {
    "public.destination": {
      "name": "destination",
      "schema": "",
      "columns": {
        "id": {
          "name": "id",
          "type": "text",
          "primaryKey": true,
          "notNull": true
        },
        "name": {
          "name": "name",
          "type": "text",
          "primaryKey": false,
          "notNull": true
        },
        "is_warehouse": {
          "name": "is_warehouse",
          "type": "boolean",
          "primaryKey": false,
          "notNull": true,
          "default": false
        },
        "created_at": {
          "name": "created_at",
          "type": "timestamp with time zone",
          "primaryKey": false,
          "notNull": true,
          "default": "now()"
        },
        "updated_at": {
          "name": "updated_at",
          "type": "timestamp with time zone",
          "primaryKey": false,
          "notNull": true,
          "default": "now()"
        }
      },
      "indexes": {},
      "foreignKeys": {},
      "compositePrimaryKeys": {},
      "uniqueConstraints": {
        "destination_name_unique": {
          "name": "destination_name_unique",
          "nullsNotDistinct": false,
          "columns": [
            "name"
          ]
        }
      },
      "policies": {},
      "checkConstraints": {},
      "isRLSEnabled": false
    },
    "public.entity": {
      "name": "entity",
      "schema": "",
      "columns": {
        "id": {
          "name": "id",
          "type": "text",
          "primaryKey": true,
          "notNull": true
        },
        "name": {
          "name": "name",
          "type": "text",
          "primaryKey": false,
          "notNull": true
        },
        "type": {
          "name": "type",
          "type": "entity_type",
          "typeSchema": "public",
          "primaryKey": false,
          "notNull": true
        },
        "unit": {
          "name": "unit",
          "type": "text",
          "primaryKey": false,
          "notNull": true
        },
        "created_at": {
          "name": "created_at",
          "type": "timestamp with time zone",
          "primaryKey": false,
          "notNull": true,
          "default": "now()"
        },
        "updated_at": {
          "name": "updated_at",
          "type": "timestamp with time zone",
          "primaryKey": false,
          "notNull": true,
          "default": "now()"
        }
      },
      "indexes": {},
      "foreignKeys": {},
      "compositePrimaryKeys": {},
      "uniqueConstraints": {
        "entity_name_unique": {
          "name": "entity_name_unique",
          "nullsNotDistinct": false,
          "columns": [
            "name"
          ]
        }
      },
      "policies": {},
      "checkConstraints": {},
      "isRLSEnabled": false
    },
    "public.entity_variant": {
      "name": "entity_variant",
      "schema": "",
      "columns": {
        "id": {
          "name": "id",
          "type": "text",
          "primaryKey": true,
          "notNull": true
        },
        "entity_id": {
          "name": "entity_id",
          "type": "text",
          "primaryKey": false,
          "notNull": false
        },
        "entity_length": {
          "name": "entity_length",
          "type": "numeric(18, 6)",
          "primaryKey": false,
          "notNull": false
        },
        "entity_width": {
          "name": "entity_width",
          "type": "numeric(18, 6)",
          "primaryKey": false,
          "notNull": false
        },
        "entity_height": {
          "name": "entity_height",
          "type": "numeric(18, 6)",
          "primaryKey": false,
          "notNull": false
        },
        "entity_thickness": {
          "name": "entity_thickness",
          "type": "numeric(18, 6)",
          "primaryKey": false,
          "notNull": false
        },
        "thickness_unit": {
          "name": "thickness_unit",
          "type": "text",
          "primaryKey": false,
          "notNull": false
        },
        "dimension_unit": {
          "name": "dimension_unit",
          "type": "text",
          "primaryKey": false,
          "notNull": false
        },
        "created_at": {
          "name": "created_at",
          "type": "timestamp with time zone",
          "primaryKey": false,
          "notNull": true,
          "default": "now()"
        },
        "updated_at": {
          "name": "updated_at",
          "type": "timestamp with time zone",
          "primaryKey": false,
          "notNull": true,
          "default": "now()"
        }
      },
      "indexes": {
        "entity_variant_entity_id_idx": {
          "name": "entity_variant_entity_id_idx",
          "columns": [
            {
              "expression": "entity_id",
              "isExpression": false,
              "asc": true,
              "nulls": "last"
            }
          ],
          "isUnique": false,
          "concurrently": false,
          "method": "btree",
          "with": {}
        }
      },
      "foreignKeys": {
        "entity_variant_entity_id_entity_id_fk": {
          "name": "entity_variant_entity_id_entity_id_fk",
          "tableFrom": "entity_variant",
          "tableTo": "entity",
          "columnsFrom": [
            "entity_id"
          ],
          "columnsTo": [
            "id"
          ],
          "onDelete": "no action",
          "onUpdate": "no action"
        }
      },
      "compositePrimaryKeys": {},
      "uniqueConstraints": {},
      "policies": {},
      "checkConstraints": {},
      "isRLSEnabled": false
    },
    "public.entity_variant_warehouse": {
      "name": "entity_variant_warehouse",
      "schema": "",
      "columns": {
        "id": {
          "name": "id",
          "type": "text",
          "primaryKey": true,
          "notNull": true
        },
        "entity_id": {
          "name": "entity_id",
          "type": "text",
          "primaryKey": false,
          "notNull": false
        },
        "entity_length": {
          "name": "entity_length",
          "type": "numeric(18, 6)",
          "primaryKey": false,
          "notNull": false
        },
        "entity_width": {
          "name": "entity_width",
          "type": "numeric(18, 6)",
          "primaryKey": false,
          "notNull": false
        },
        "entity_height": {
          "name": "entity_height",
          "type": "numeric(18, 6)",
          "primaryKey": false,
          "notNull": false
        },
        "entity_thickness": {
          "name": "entity_thickness",
          "type": "numeric(18, 6)",
          "primaryKey": false,
          "notNull": false
        },
        "thickness_unit": {
          "name": "thickness_unit",
          "type": "text",
          "primaryKey": false,
          "notNull": false
        },
        "dimension_unit": {
          "name": "dimension_unit",
          "type": "text",
          "primaryKey": false,
          "notNull": false
        },
        "created_at": {
          "name": "created_at",
          "type": "timestamp with time zone",
          "primaryKey": false,
          "notNull": true,
          "default": "now()"
        },
        "updated_at": {
          "name": "updated_at",
          "type": "timestamp with time zone",
          "primaryKey": false,
          "notNull": true,
          "default": "now()"
        }
      },
      "indexes": {
        "entity_variant_warehouse_entity_id_idx": {
          "name": "entity_variant_warehouse_entity_id_idx",
          "columns": [
            {
              "expression": "entity_id",
              "isExpression": false,
              "asc": true,
              "nulls": "last"
            }
          ],
          "isUnique": false,
          "concurrently": false,
          "method": "btree",
          "with": {}
        }
      },
      "foreignKeys": {
        "entity_variant_warehouse_entity_id_entity_warehouse_id_fk": {
          "name": "entity_variant_warehouse_entity_id_entity_warehouse_id_fk",
          "tableFrom": "entity_variant_warehouse",
          "tableTo": "entity_warehouse",
          "columnsFrom": [
            "entity_id"
          ],
          "columnsTo": [
            "id"
          ],
          "onDelete": "no action",
          "onUpdate": "no action"
        }
      },
      "compositePrimaryKeys": {},
      "uniqueConstraints": {},
      "policies": {},
      "checkConstraints": {},
      "isRLSEnabled": false
    },
    "public.entity_warehouse": {
      "name": "entity_warehouse",
      "schema": "",
      "columns": {
        "id": {
          "name": "id",
          "type": "text",
          "primaryKey": true,
          "notNull": true
        },
        "name": {
          "name": "name",
          "type": "text",
          "primaryKey": false,
          "notNull": true
        },
        "type": {
          "name": "type",
          "type": "entity_type",
          "typeSchema": "public",
          "primaryKey": false,
          "notNull": true
        },
        "unit": {
          "name": "unit",
          "type": "text",
          "primaryKey": false,
          "notNull": true
        },
        "created_at": {
          "name": "created_at",
          "type": "timestamp with time zone",
          "primaryKey": false,
          "notNull": true,
          "default": "now()"
        },
        "updated_at": {
          "name": "updated_at",
          "type": "timestamp with time zone",
          "primaryKey": false,
          "notNull": true,
          "default": "now()"
        }
      },
      "indexes": {},
      "foreignKeys": {},
      "compositePrimaryKeys": {},
      "uniqueConstraints": {
        "entity_warehouse_name_unique": {
          "name": "entity_warehouse_name_unique",
          "nullsNotDistinct": false,
          "columns": [
            "name"
          ]
        }
      },
      "policies": {},
      "checkConstraints": {},
      "isRLSEnabled": false
    },
    "public.transaction": {
      "name": "transaction",
      "schema": "",
      "columns": {
        "id": {
          "name": "id",
          "type": "text",
          "primaryKey": true,
          "notNull": true
        },
        "entity_id": {
          "name": "entity_id",
          "type": "text",
          "primaryKey": false,
          "notNull": false
        },
        "entity_variant_id": {
          "name": "entity_variant_id",
          "type": "text",
          "primaryKey": false,
          "notNull": false
        },
        "destination_id": {
          "name": "destination_id",
          "type": "text",
          "primaryKey": false,
          "notNull": false
        },
        "status": {
          "name": "status",
          "type": "payment_status",
          "typeSchema": "public",
          "primaryKey": false,
          "notNull": true
        },
        "transportation_cost_id": {
          "name": "transportation_cost_id",
          "type": "text",
          "primaryKey": false,
          "notNull": false
        },
        "quantity": {
          "name": "quantity",
          "type": "numeric(18, 6)",
          "primaryKey": false,
          "notNull": false
        },
        "type": {
          "name": "type",
          "type": "transaction_type",
          "typeSchema": "public",
          "primaryKey": false,
          "notNull": false
        },
        "rate": {
          "name": "rate",
          "type": "numeric(18, 6)",
          "primaryKey": false,
          "notNull": false
        },
        "amount": {
          "name": "amount",
          "type": "numeric(18, 2)",
          "primaryKey": false,
          "notNull": false
        },
        "created_at": {
          "name": "created_at",
          "type": "timestamp with time zone",
          "primaryKey": false,
          "notNull": true,
          "default": "now()"
        },
        "updated_at": {
          "name": "updated_at",
          "type": "timestamp with time zone",
          "primaryKey": false,
          "notNull": true,
          "default": "now()"
        }
      },
      "indexes": {
        "transaction_entity_id_idx": {
          "name": "transaction_entity_id_idx",
          "columns": [
            {
              "expression": "entity_id",
              "isExpression": false,
              "asc": true,
              "nulls": "last"
            }
          ],
          "isUnique": false,
          "concurrently": false,
          "method": "btree",
          "with": {}
        },
        "transaction_destination_id_idx": {
          "name": "transaction_destination_id_idx",
          "columns": [
            {
              "expression": "destination_id",
              "isExpression": false,
              "asc": true,
              "nulls": "last"
            }
          ],
          "isUnique": false,
          "concurrently": false,
          "method": "btree",
          "with": {}
        },
        "transaction_created_at_idx": {
          "name": "transaction_created_at_idx",
          "columns": [
            {
              "expression": "created_at",
              "isExpression": false,
              "asc": true,
              "nulls": "last"
            }
          ],
          "isUnique": false,
          "concurrently": false,
          "method": "btree",
          "with": {}
        }
      },
      "foreignKeys": {
        "transaction_entity_id_entity_id_fk": {
          "name": "transaction_entity_id_entity_id_fk",
          "tableFrom": "transaction",
          "tableTo": "entity",
          "columnsFrom": [
            "entity_id"
          ],
          "columnsTo": [
            "id"
          ],
          "onDelete": "no action",
          "onUpdate": "no action"
        },
        "transaction_entity_variant_id_entity_variant_id_fk": {
          "name": "transaction_entity_variant_id_entity_variant_id_fk",
          "tableFrom": "transaction",
          "tableTo": "entity_variant",
          "columnsFrom": [
            "entity_variant_id"
          ],
          "columnsTo": [
            "id"
          ],
          "onDelete": "no action",
          "onUpdate": "no action"
        },
        "transaction_destination_id_destination_id_fk": {
          "name": "transaction_destination_id_destination_id_fk",
          "tableFrom": "transaction",
          "tableTo": "destination",
          "columnsFrom": [
            "destination_id"
          ],
          "columnsTo": [
            "id"
          ],
          "onDelete": "no action",
          "onUpdate": "no action"
        },
        "transaction_transportation_cost_id_transportation_cost_id_fk": {
          "name": "transaction_transportation_cost_id_transportation_cost_id_fk",
          "tableFrom": "transaction",
          "tableTo": "transportation_cost",
          "columnsFrom": [
            "transportation_cost_id"
          ],
          "columnsTo": [
            "id"
          ],
          "onDelete": "no action",
          "onUpdate": "no action"
        }
      },
      "compositePrimaryKeys": {},
      "uniqueConstraints": {},
      "policies": {},
      "checkConstraints": {},
      "isRLSEnabled": false
    },
    "public.transportation_cost": {
      "name": "transportation_cost",
      "schema": "",
      "columns": {
        "id": {
          "name": "id",
          "type": "text",
          "primaryKey": true,
          "notNull": true
        },
        "entity_id": {
          "name": "entity_id",
          "type": "text",
          "primaryKey": false,
          "notNull": false
        },
        "vehicle_type": {
          "name": "vehicle_type",
          "type": "text",
          "primaryKey": false,
          "notNull": false,
          "default": "''"
        },
        "reg_no": {
          "name": "reg_no",
          "type": "text",
          "primaryKey": false,
          "notNull": true,
          "default": "''"
        },
        "cost": {
          "name": "cost",
          "type": "numeric(18, 2)",
          "primaryKey": false,
          "notNull": true,
          "default": "'0'"
        }
      },
      "indexes": {},
      "foreignKeys": {
        "transportation_cost_entity_id_entity_id_fk": {
          "name": "transportation_cost_entity_id_entity_id_fk",
          "tableFrom": "transportation_cost",
          "tableTo": "entity",
          "columnsFrom": [
            "entity_id"
          ],
          "columnsTo": [
            "id"
          ],
          "onDelete": "no action",
          "onUpdate": "no action"
        }
      },
      "compositePrimaryKeys": {},
      "uniqueConstraints": {},
      "policies": {},
      "checkConstraints": {},
      "isRLSEnabled": false
    },
    "public.warehouse_transaction": {
      "name": "warehouse_transaction",
      "schema": "",
      "columns": {
        "id": {
          "name": "id",
          "type": "text",
          "primaryKey": true,
          "notNull": true
        },
        "entity_id": {
          "name": "entity_id",
          "type": "text",
          "primaryKey": false,
          "notNull": false
        },
        "entity_variant_id": {
          "name": "entity_variant_id",
          "type": "text",
          "primaryKey": false,
          "notNull": false
        },
        "source_id": {
          "name": "source_id",
          "type": "text",
          "primaryKey": false,
          "notNull": false
        },
        "destination_id": {
          "name": "destination_id",
          "type": "text",
          "primaryKey": false,
          "notNull": false
        },
        "quantity": {
          "name": "quantity",
          "type": "numeric(18, 6)",
          "primaryKey": false,
          "notNull": false
        },
        "type": {
          "name": "type",
          "type": "transaction_type",
          "typeSchema": "public",
          "primaryKey": false,
          "notNull": false
        },
        "created_at": {
          "name": "created_at",
          "type": "timestamp with time zone",
          "primaryKey": false,
          "notNull": true,
          "default": "now()"
        },
        "updated_at": {
          "name": "updated_at",
          "type": "timestamp with time zone",
          "primaryKey": false,
          "notNull": true,
          "default": "now()"
        }
      },
      "indexes": {
        "warehouse_transaction_entity_id_idx": {
          "name": "warehouse_transaction_entity_id_idx",
          "columns": [
            {
              "expression": "entity_id",
              "isExpression": false,
              "asc": true,
              "nulls": "last"
            }
          ],
          "isUnique": false,
          "concurrently": false,
          "method": "btree",
          "with": {}
        },
        "warehouse_transaction_source_id_idx": {
          "name": "warehouse_transaction_source_id_idx",
          "columns": [
            {
              "expression": "source_id",
              "isExpression": false,
              "asc": true,
              "nulls": "last"
            }
          ],
          "isUnique": false,
          "concurrently": false,
          "method": "btree",
          "with": {}
        },
        "warehouse_transaction_destination_id_idx": {
          "name": "warehouse_transaction_destination_id_idx",
          "columns": [
            {
              "expression": "destination_id",
              "isExpression": false,
              "asc": true,
              "nulls": "last"
            }
          ],
          "isUnique": false,
          "concurrently": false,
          "method": "btree",
          "with": {}
        },
        "warehouse_transaction_created_at_idx": {
          "name": "warehouse_transaction_created_at_idx",
          "columns": [
            {
              "expression": "created_at",
              "isExpression": false,
              "asc": true,
              "nulls": "last"
            }
          ],
          "isUnique": false,
          "concurrently": false,
          "method": "btree",
          "with": {}
        }
      },
      "foreignKeys": {
        "warehouse_transaction_entity_id_entity_warehouse_id_fk": {
          "name": "warehouse_transaction_entity_id_entity_warehouse_id_fk",
          "tableFrom": "warehouse_transaction",
          "tableTo": "entity_warehouse",
          "columnsFrom": [
            "entity_id"
          ],
          "columnsTo": [
            "id"
          ],
          "onDelete": "no action",
          "onUpdate": "no action"
        },
        "warehouse_transaction_entity_variant_id_entity_variant_warehouse_id_fk": {
          "name": "warehouse_transaction_entity_variant_id_entity_variant_warehouse_id_fk",
          "tableFrom": "warehouse_transaction",
          "tableTo": "entity_variant_warehouse",
          "columnsFrom": [
            "entity_variant_id"
          ],
          "columnsTo": [
            "id"
          ],
          "onDelete": "no action",
          "onUpdate": "no action"
        },
        "warehouse_transaction_source_id_destination_id_fk": {
          "name": "warehouse_transaction_source_id_destination_id_fk",
          "tableFrom": "warehouse_transaction",
          "tableTo": "destination",
          "columnsFrom": [
            "source_id"
          ],
          "columnsTo": [
            "id"
          ],
          "onDelete": "no action",
          "onUpdate": "no action"
        },
        "warehouse_transaction_destination_id_destination_id_fk": {
          "name": "warehouse_transaction_destination_id_destination_id_fk",
          "tableFrom": "warehouse_transaction",
          "tableTo": "destination",
          "columnsFrom": [
            "destination_id"
          ],
          "columnsTo": [
            "id"
          ],
          "onDelete": "no action",
          "onUpdate": "no action"
        }
      },
      "compositePrimaryKeys": {},
      "uniqueConstraints": {},
      "policies": {},
      "checkConstraints": {},
      "isRLSEnabled": false
    },
    "public.account": {
      "name": "account",
      "schema": "",
      "columns": {
        "id": {
          "name": "id",
          "type": "text",
          "primaryKey": true,
          "notNull": true
        },
        "account_id": {
          "name": "account_id",
          "type": "text",
          "primaryKey": false,
          "notNull": true
        },
        "provider_id": {
          "name": "provider_id",
          "type": "text",
          "primaryKey": false,
          "notNull": true
        },
        "user_id": {
          "name": "user_id",
          "type": "text",
          "primaryKey": false,
          "notNull": true
        },
        "access_token": {
          "name": "access_token",
          "type": "text",
          "primaryKey": false,
          "notNull": false
        },
        "refresh_token": {
          "name": "refresh_token",
          "type": "text",
          "primaryKey": false,
          "notNull": false
        },
        "id_token": {
          "name": "id_token",
          "type": "text",
          "primaryKey": false,
          "notNull": false
        },
        "access_token_expires_at": {
          "name": "access_token_expires_at",
          "type": "bigint",
          "primaryKey": false,
          "notNull": false
        },
        "refresh_token_expires_at": {
          "name": "refresh_token_expires_at",
          "type": "bigint",
          "primaryKey": false,
          "notNull": false
        },
        "scope": {
          "name": "scope",
          "type": "text",
          "primaryKey": false,
          "notNull": false
        },
        "password": {
          "name": "password",
          "type": "text",
          "primaryKey": false,
          "notNull": false
        },
        "created_at": {
          "name": "created_at",
          "type": "bigint",
          "primaryKey": false,
          "notNull": true,
          "default": "(extract(epoch from now()) * 1000)::bigint"
        },
        "updated_at": {
          "name": "updated_at",
          "type": "bigint",
          "primaryKey": false,
          "notNull": true,
          "default": "(extract(epoch from now()) * 1000)::bigint"
        }
      },
      "indexes": {
        "account_userId_idx": {
          "name": "account_userId_idx",
          "columns": [
            {
              "expression": "user_id",
              "isExpression": false,
              "asc": true,
              "nulls": "last"
            }
          ],
          "isUnique": false,
          "concurrently": false,
          "method": "btree",
          "with": {}
        }
      },
      "foreignKeys": {
        "account_user_id_user_id_fk": {
          "name": "account_user_id_user_id_fk",
          "tableFrom": "account",
          "tableTo": "user",
          "columnsFrom": [
            "user_id"
          ],
          "columnsTo": [
            "id"
          ],
          "onDelete": "cascade",
          "onUpdate": "no action"
        }
      },
      "compositePrimaryKeys": {},
      "uniqueConstraints": {},
      "policies": {},
      "checkConstraints": {},
      "isRLSEnabled": false
    },
    "public.session": {
      "name": "session",
      "schema": "",
      "columns": {
        "id": {
          "name": "id",
          "type": "text",
          "primaryKey": true,
          "notNull": true
        },
        "expires_at": {
          "name": "expires_at",
          "type": "bigint",
          "primaryKey": false,
          "notNull": true
        },
        "token": {
          "name": "token",
          "type": "text",
          "primaryKey": false,
          "notNull": true
        },
        "created_at": {
          "name": "created_at",
          "type": "bigint",
          "primaryKey": false,
          "notNull": true,
          "default": "(extract(epoch from now()) * 1000)::bigint"
        },
        "updated_at": {
          "name": "updated_at",
          "type": "bigint",
          "primaryKey": false,
          "notNull": true,
          "default": "(extract(epoch from now()) * 1000)::bigint"
        },
        "ip_address": {
          "name": "ip_address",
          "type": "text",
          "primaryKey": false,
          "notNull": false
        },
        "user_agent": {
          "name": "user_agent",
          "type": "text",
          "primaryKey": false,
          "notNull": false
        },
        "user_id": {
          "name": "user_id",
          "type": "text",
          "primaryKey": false,
          "notNull": true
        }
      },
      "indexes": {
        "session_userId_idx": {
          "name": "session_userId_idx",
          "columns": [
            {
              "expression": "user_id",
              "isExpression": false,
              "asc": true,
              "nulls": "last"
            }
          ],
          "isUnique": false,
          "concurrently": false,
          "method": "btree",
          "with": {}
        }
      },
      "foreignKeys": {
        "session_user_id_user_id_fk": {
          "name": "session_user_id_user_id_fk",
          "tableFrom": "session",
          "tableTo": "user",
          "columnsFrom": [
            "user_id"
          ],
          "columnsTo": [
            "id"
          ],
          "onDelete": "cascade",
          "onUpdate": "no action"
        }
      },
      "compositePrimaryKeys": {},
      "uniqueConstraints": {
        "session_token_unique": {
          "name": "session_token_unique",
          "nullsNotDistinct": false,
          "columns": [
            "token"
          ]
        }
      },
      "policies": {},
      "checkConstraints": {},
      "isRLSEnabled": false
    },
    "public.user": {
      "name": "user",
      "schema": "",
      "columns": {
        "id": {
          "name": "id",
          "type": "text",
          "primaryKey": true,
          "notNull": true
        },
        "name": {
          "name": "name",
          "type": "text",
          "primaryKey": false,
          "notNull": true
        },
        "email": {
          "name": "email",
          "type": "text",
          "primaryKey": false,
          "notNull": true
        },
        "email_verified": {
          "name": "email_verified",
          "type": "boolean",
          "primaryKey": false,
          "notNull": true,
          "default": false
        },
        "image": {
          "name": "image",
          "type": "text",
          "primaryKey": false,
          "notNull": false
        },
        "role": {
          "name": "role",
          "type": "text",
          "primaryKey": false,
          "notNull": true,
          "default": "'user'"
        },
        "created_at": {
          "name": "created_at",
          "type": "bigint",
          "primaryKey": false,
          "notNull": true,
          "default": "(extract(epoch from now()) * 1000)::bigint"
        },
        "updated_at": {
          "name": "updated_at",
          "type": "bigint",
          "primaryKey": false,
          "notNull": true,
          "default": "(extract(epoch from now()) * 1000)::bigint"
        }
      },
      "indexes": {},
      "foreignKeys": {},
      "compositePrimaryKeys": {},
      "uniqueConstraints": {
        "user_email_unique": {
          "name": "user_email_unique",
          "nullsNotDistinct": false,
          "columns": [
            "email"
          ]
        }
      },
      "policies": {},
      "checkConstraints": {},
      "isRLSEnabled": false
    },
    "public.verification": {
      "name": "verification",
      "schema": "",
      "columns": {
        "id": {
          "name": "id",
          "type": "text",
          "primaryKey": true,
          "notNull": true
        },
        "identifier": {
          "name": "identifier",
          "type": "text",
          "primaryKey": false,
          "notNull": true
        },
        "value": {
          "name": "value",
          "type": "text",
          "primaryKey": false,
          "notNull": true
        },
        "expires_at": {
          "name": "expires_at",
          "type": "bigint",
          "primaryKey": false,
          "notNull": true
        },
        "created_at": {
          "name": "created_at",
          "type": "bigint",
          "primaryKey": false,
          "notNull": true,
          "default": "(extract(epoch from now()) * 1000)::bigint"
        },
        "updated_at": {
          "name": "updated_at",
          "type": "bigint",
          "primaryKey": false,
          "notNull": true,
          "default": "(extract(epoch from now()) * 1000)::bigint"
        }
      },
      "indexes": {
        "verification_identifier_idx": {
          "name": "verification_identifier_idx",
          "columns": [
            {
              "expression": "identifier",
              "isExpression": false,
              "asc": true,
              "nulls": "last"
            }
          ],
          "isUnique": false,
          "concurrently": false,
          "method": "btree",
          "with": {}
        }
      },
      "foreignKeys": {},
      "compositePrimaryKeys": {},
      "uniqueConstraints": {},
      "policies": {},
      "checkConstraints": {},
      "isRLSEnabled": false
    }
  },
  "enums": {
    "public.entity_type": {
      "name": "entity_type",
      "schema": "public",
      "values": [
        "payroll",
        "cash"
      ]
    },
    "public.payment_status": {
      "name": "payment_status",
      "schema": "public",
      "values": [
        "paid",
        "pending",
        "advance"
      ]
    },
    "public.transaction_type": {
      "name": "transaction_type",
      "schema": "public",
      "values": [
        "credit",
        "debit"
      ]
    }
  },
  "schemas": {},
  "sequences": {},
  "roles": {},
  "policies": {},
  "views": {},
  "_meta": {
    "columns": {},
    "schemas": {},
    "tables": {}
  }
}